odoo/addons/ladirecta_website_sale/README.md
odoo/addons/ladirecta_website_sale/__init__.py
odoo/addons/ladirecta_website_sale/__manifest__.py
odoo/addons/ladirecta_website_sale/controllers/__init__.py
odoo/addons/ladirecta_website_sale/controllers/controller.py
odoo/addons/ladirecta_website_sale/data/data.xml
odoo/addons/ladirecta_website_sale/i18n/ca_ES.po
odoo/addons/ladirecta_website_sale/models/__init__.py
odoo/addons/ladirecta_website_sale/models/res_partner.py
odoo/addons/ladirecta_website_sale/views/website_templates.xml
odoo_addon_ladirecta_website_sale-16.0.0.0.2.dist-info/METADATA
odoo_addon_ladirecta_website_sale-16.0.0.0.2.dist-info/WHEEL
odoo_addon_ladirecta_website_sale-16.0.0.0.2.dist-info/top_level.txt
odoo_addon_ladirecta_website_sale-16.0.0.0.2.dist-info/RECORD
