Metadata-Version: 2.4
Name: odoo-addon-ladirecta_website_sale
Version: 16.0.0.0.2
Summary: La Directa Website Sale customizations
Home-page: https://git.coopdevs.org/talaios/addons/odoo-directa#
Author: Coopdevs Treball SCCL
License: AGPL-3
Classifier: Programming Language :: Python
Classifier: Framework :: Odoo
Classifier: Framework :: Odoo :: 16.0
Classifier: License :: OSI Approved :: GNU Affero General Public License v3
Requires-Python: >=3.10
Requires-Dist: odoo-addon-ladirecta<16.1dev,>=16.0dev
Requires-Dist: odoo-addon-partner_contact_birthdate<16.1dev,>=16.0dev
Requires-Dist: odoo-addon-partner_contact_birthplace<16.1dev,>=16.0dev
Requires-Dist: odoo-addon-partner_contact_gender<16.1dev,>=16.0dev
Requires-Dist: odoo-addon-partner_firstname<16.1dev,>=16.0dev
Requires-Dist: odoo<16.1dev,>=16.0a
Dynamic: author
Dynamic: classifier
Dynamic: home-page
Dynamic: license
Dynamic: requires-dist
Dynamic: requires-python
Dynamic: summary
